{
  "providers": {
    "aws": {
      "name": "Amazon AWS",
      "slug": "aws",
      "providerId": "3bb5a379-472f-4c84-9ba4-3337f3922582",
      "features": {
        "gpuSelection": {
          "score": 9,
          "available": true,
          "models": ["P4 (A100)", "P3 (V100)", "G5 (A10G)", "G4 (T4)"],
          "latestGeneration": true,
          "multiGPU": true,
          "bareMetalAccess": false,
          "notes": "Extensive selection of GPU instance types optimized for different workloads"
        },
        "pricing": {
          "score": 7,
          "flexible": true,
          "model": "hourly",
          "minimumCommitment": "none",
          "averageCostRange": "$1.50-$15.00/hr per GPU",
          "spotPricing": true,
          "reservedDiscounts": true,
          "transparentPricing": false,
          "notes": "Complex pricing structure but offers various discount options"
        },
        "performance": {
          "score": 9,
          "networkSpeed": "excellent",
          "storageSpeed": "excellent",
          "cpuPerformance": "excellent",
          "gpuInterconnect": "nvlink",
          "bandwidth": "400 Gbps (P4)",
          "notes": "Industry-leading performance with optimized networking"
        },
        "scalability": {
          "score": 10,
          "autoScaling": true,
          "maxGPUs": "unlimited",
          "multiRegion": true,
          "loadBalancing": true,
          "orchestration": "EKS, ECS",
          "notes": "Unlimited scalability with global infrastructure"
        },
        "support": {
          "score": 8,
          "documentation": "excellent",
          "communitySupport": "excellent",
          "technicalSupport": "tiered",
          "responsiveness": "varies by plan",
          "expertise": "high",
          "notes": "Extensive documentation, paid support tiers available"
        },
        "developerExperience": {
          "score": 7,
          "easeOfUse": "complex",
          "api": "comprehensive",
          "cli": "aws-cli",
          "dashboard": "complex",
          "setupTime": "medium",
          "notes": "Powerful but complex, steep learning curve"
        },
        "security": {
          "score": 10,
          "compliance": ["SOC", "HIPAA", "FedRAMP", "ISO27001"],
          "encryption": true,
          "networkSecurity": "VPC, security groups",
          "accessControl": "IAM",
          "auditLogging": true,
          "notes": "Industry-leading security and compliance certifications"
        },
        "geographicCoverage": {
          "score": 10,
          "regions": 25,
          "availabilityZones": 80,
          "globalPresence": "extensive",
          "latency": "low",
          "notes": "Most extensive global coverage"
        }
      },
      "pros": [
        "Most comprehensive GPU selection and instance types",
        "Unmatched global infrastructure and availability",
        "Extensive ecosystem of integrated services",
        "Multiple pricing options (on-demand, reserved, spot)",
        "Industry-leading security and compliance",
        "Mature platform with extensive documentation"
      ],
      "cons": [
        "Complex pricing structure can lead to unexpected costs",
        "Steep learning curve for new users",
        "Most expensive option for simple use cases",
        "Overwhelming number of service options",
        "Limited customer support on basic plans"
      ],
      "bestFor": [
        "Enterprise deployments requiring comprehensive services",
        "Applications needing global distribution",
        "Workloads requiring highest security and compliance",
        "Complex multi-service architectures",
        "Organizations already using AWS ecosystem"
      ],
      "pricing": {
        "model": "hourly",
        "minimumCommitment": "none",
        "averageCostRange": "$1.50-$15.00/hr per GPU",
        "billingIncrement": "per second",
        "additionalFees": "data transfer, storage"
      },
      "strengths": [
        "Market leader with proven reliability",
        "Unmatched service ecosystem",
        "Global infrastructure coverage",
        "Advanced networking and security features"
      ],
      "weaknesses": [
        "Pricing complexity",
        "Learning curve complexity",
        "Cost optimization challenges"
      ],
      "uniqueFeatures": [
        "SageMaker ML platform integration",
        "Spot instance marketplace",
        "Capacity Blocks for ML training",
        "EFA (Elastic Fabric Adapter) for HPC"
      ]
    },
    "runpod": {
      "name": "RunPod",
      "slug": "runpod", 
      "providerId": "30a69dae-5939-499a-a4f5-5114797dcdb3",
      "features": {
        "gpuSelection": {
          "score": 8,
          "available": true,
          "models": ["H100", "A100", "A6000", "RTX 4090", "RTX 3090"],
          "latestGeneration": true,
          "multiGPU": true,
          "bareMetalAccess": false,
          "notes": "Wide variety of GPU options from consumer to enterprise"
        },
        "pricing": {
          "score": 9,
          "flexible": true,
          "model": "per-second",
          "minimumCommitment": "none",
          "averageCostRange": "$0.30-$4.00/hr per GPU",
          "spotPricing": true,
          "reservedDiscounts": false,
          "transparentPricing": true,
          "notes": "Competitive pricing with clear, transparent structure"
        },
        "performance": {
          "score": 7,
          "networkSpeed": "good",
          "storageSpeed": "good",
          "cpuPerformance": "good",
          "gpuInterconnect": "varies",
          "bandwidth": "varies",
          "notes": "Good performance, can vary by region and availability"
        },
        "scalability": {
          "score": 6,
          "autoScaling": true,
          "maxGPUs": "limited by availability",
          "multiRegion": true,
          "loadBalancing": false,
          "orchestration": "API",
          "notes": "Scaling limited by GPU availability in network"
        },
        "support": {
          "score": 6,
          "documentation": "good",
          "communitySupport": "Discord",
          "technicalSupport": "community",
          "responsiveness": "varies",
          "expertise": "community-driven",
          "notes": "Community-focused support, Discord server"
        },
        "developerExperience": {
          "score": 9,
          "easeOfUse": "excellent",
          "api": "good",
          "cli": "basic",
          "dashboard": "intuitive",
          "setupTime": "fast",
          "notes": "User-friendly interface, quick setup"
        },
        "security": {
          "score": 7,
          "compliance": ["SOC 2"],
          "encryption": true,
          "networkSecurity": "standard",
          "accessControl": "API keys",
          "auditLogging": "basic",
          "notes": "Standard security features, suitable for most workloads"
        },
        "geographicCoverage": {
          "score": 6,
          "regions": 8,
          "availabilityZones": "multiple",
          "globalPresence": "moderate",
          "latency": "varies",
          "notes": "Growing global presence, some regions limited"
        }
      },
      "pros": [
        "Very competitive pricing with transparent structure",
        "User-friendly interface and quick setup",
        "Pay-per-second billing for cost optimization",
        "Wide variety of GPU options available",
        "Good for development and experimentation",
        "Active community support"
      ],
      "cons": [
        "GPU availability can be inconsistent",
        "Limited enterprise features compared to major clouds",
        "Support primarily community-based",
        "Performance can vary by region",
        "Less mature ecosystem of services"
      ],
      "bestFor": [
        "Individual developers and small teams",
        "Cost-conscious AI/ML experimentation",
        "Short-term or burst compute needs",
        "Prototyping and development workloads",
        "Users wanting simple, transparent pricing"
      ],
      "pricing": {
        "model": "per-second",
        "minimumCommitment": "none",
        "averageCostRange": "$0.30-$4.00/hr per GPU",
        "billingIncrement": "per second",
        "additionalFees": "minimal"
      },
      "strengths": [
        "Exceptional value for money",
        "Simple, intuitive platform",
        "Quick deployment times",
        "Flexible GPU options"
      ],
      "weaknesses": [
        "Limited enterprise features",
        "Inconsistent GPU availability",
        "Community-driven support model"
      ],
      "uniqueFeatures": [
        "Spot-to-on-demand fallback",
        "Hot-reload development environment",
        "SSH and VS Code tunnel integration",
        "Template marketplace"
      ]
    },
    "coreweave": {
      "name": "CoreWeave",
      "slug": "coreweave",
      "providerId": "1d434a66-bf40-40a8-8e80-d5ab48b6d27f",
      "features": {
        "gpuSelection": {
          "score": 9,
          "available": true,
          "models": ["H100", "A100", "A40", "RTX 6000", "RTX A6000"],
          "latestGeneration": true,
          "multiGPU": true,
          "bareMetalAccess": true,
          "notes": "Extensive NVIDIA GPU selection, latest models available"
        },
        "pricing": {
          "score": 9,
          "flexible": true,
          "model": "per-second",
          "minimumCommitment": "none", 
          "averageCostRange": "$0.80-$4.50/hr per GPU",
          "spotPricing": false,
          "reservedDiscounts": true,
          "transparentPricing": true,
          "notes": "Very competitive pricing, up to 80% less than legacy providers"
        },
        "performance": {
          "score": 9,
          "networkSpeed": "excellent",
          "storageSpeed": "excellent",
          "cpuPerformance": "excellent",
          "gpuInterconnect": "nvlink",
          "bandwidth": "very high",
          "notes": "Kubernetes-native with bare metal performance"
        },
        "scalability": {
          "score": 10,
          "autoScaling": true,
          "maxGPUs": "thousands",
          "multiRegion": false,
          "loadBalancing": true,
          "orchestration": "Kubernetes",
          "notes": "Access thousands of GPUs in seconds, Kubernetes-native"
        },
        "support": {
          "score": 8,
          "documentation": "good",
          "communitySupport": "specialized",
          "technicalSupport": "dedicated",
          "responsiveness": "excellent",
          "expertise": "GPU-specialized",
          "notes": "Specialized GPU expertise and dedicated support"
        },
        "developerExperience": {
          "score": 8,
          "easeOfUse": "good",
          "api": "kubernetes",
          "cli": "kubectl",
          "dashboard": "kubernetes",
          "setupTime": "fast",
          "notes": "Kubernetes-native, familiar to container users"
        },
        "security": {
          "score": 8,
          "compliance": ["SOC 2"],
          "encryption": true,
          "networkSecurity": "kubernetes",
          "accessControl": "RBAC",
          "auditLogging": true,
          "notes": "Enterprise-grade security with Kubernetes RBAC"
        },
        "geographicCoverage": {
          "score": 6,
          "regions": 4,
          "availabilityZones": "multiple",
          "globalPresence": "North America focused",
          "latency": "low in covered regions",
          "notes": "Primary focus on North American data centers"
        }
      },
      "pros": [
        "Up to 80% cost savings vs traditional cloud providers",
        "Kubernetes-native infrastructure",
        "Access to latest NVIDIA GPUs including H100",
        "Rapid deployment (seconds to access thousands of GPUs)",
        "NVIDIA Elite Cloud Solutions Provider",
        "Specialized GPU expertise and support"
      ],
      "cons": [
        "Limited to North American regions",
        "Kubernetes learning curve for non-container users",
        "Newer player compared to major cloud providers",
        "Limited non-GPU services compared to hyperscalers"
      ],
      "bestFor": [
        "AI/ML workloads requiring latest GPUs",
        "Organizations using Kubernetes infrastructure",
        "Cost-sensitive high-performance computing",
        "VFX rendering and batch processing",
        "Users needing rapid GPU scaling"
      ],
      "pricing": {
        "model": "per-second", 
        "minimumCommitment": "none",
        "averageCostRange": "$0.80-$4.50/hr per GPU",
        "billingIncrement": "per second",
        "additionalFees": "minimal"
      },
      "strengths": [
        "Exceptional GPU price-performance",
        "Kubernetes-native architecture",
        "Latest GPU availability",
        "Rapid scaling capabilities"
      ],
      "weaknesses": [
        "Regional limitations",
        "Kubernetes complexity for some users",
        "Limited broader cloud services"
      ],
      "uniqueFeatures": [
        "Fully-managed serverless Kubernetes",
        "Bare metal performance in containers",
        "NVIDIA Elite Partnership benefits",
        "Specialized GPU-optimized infrastructure"
      ]
    }
  },
  "comparisons": {
    "aws-vs-runpod": {
      "providers": ["aws", "runpod"],
      "summary": "AWS offers comprehensive enterprise features with global coverage, while RunPod provides cost-effective GPU access with transparent pricing. AWS excels in scalability and enterprise services, while RunPod is ideal for developers and cost-conscious users.",
      "recommendation": "Choose AWS for enterprise deployments requiring comprehensive services and global reach. Choose RunPod for development, experimentation, and cost-sensitive projects.",
      "keyDifferences": [
        "AWS provides enterprise-grade services while RunPod focuses on simplicity",
        "RunPod offers significantly more transparent and competitive pricing",
        "AWS has global infrastructure while RunPod has limited regional coverage",
        "RunPod provides better developer experience for simple use cases"
      ],
      "useCaseMapping": [
        {
          "useCase": "Development & Testing",
          "recommendation": "runpod",
          "reason": "Per-second billing and simple interface ideal for development cycles"
        },
        {
          "useCase": "Enterprise Production",
          "recommendation": "aws",
          "reason": "Comprehensive enterprise features and global infrastructure"
        },
        {
          "useCase": "Cost-Sensitive Projects",
          "recommendation": "runpod",
          "reason": "Transparent pricing and competitive rates"
        }
      ]
    }
  },
  "metadata": {
    "version": "1.0",
    "lastUpdated": "2025-08-21",
    "dataSource": "provider documentation and market analysis",
    "scoringMethodology": "Normalized 1-10 scale based on feature availability, performance, and user feedback"
  }
}